acto/__init__.py
acto/errors.py
acto/version.py
acto/access/__init__.py
acto/access/models.py
acto/access/solana_gate.py
acto/cache/__init__.py
acto/cache/backend.py
acto/client/__init__.py
acto/client/async_client.py
acto/client/exceptions.py
acto/client/models.py
acto/client/sync_client.py
acto/config/__init__.py
acto/config/settings.py
acto/crypto/__init__.py
acto/crypto/hashing.py
acto/crypto/keys.py
acto/crypto/signing.py
acto/fleet/__init__.py
acto/fleet/models.py
acto/fleet/store.py
acto/logging/__init__.py
acto/logging/logger.py
acto/metrics/__init__.py
acto/metrics/registry.py
acto/pipeline/__init__.py
acto/pipeline/pipeline.py
acto/pipeline/steps.py
acto/plugins/__init__.py
acto/plugins/loader.py
acto/proof/__init__.py
acto/proof/async_engine.py
acto/proof/batch.py
acto/proof/chaining.py
acto/proof/comparison.py
acto/proof/engine.py
acto/proof/merging.py
acto/proof/models.py
acto/proof/versioning.py
acto/registry/__init__.py
acto/registry/async_service.py
acto/registry/db.py
acto/registry/models.py
acto/registry/search.py
acto/registry/service.py
acto/registry/user_models.py
acto/reputation/__init__.py
acto/reputation/scorer.py
acto/security/__init__.py
acto/security/api_key_store.py
acto/security/api_keys.py
acto/security/audit.py
acto/security/auth.py
acto/security/encryption.py
acto/security/jwt.py
acto/security/key_rotation.py
acto/security/rate_limit.py
acto/security/rbac.py
acto/security/secrets.py
acto/security/tls.py
acto/security/user_store.py
acto/security/wallet_auth.py
acto/telemetry/__init__.py
acto/telemetry/models.py
acto/telemetry/normalizer.py
acto/telemetry/parsers.py
acto/telemetry/pii.py
acto/telemetry/validator.py
acto/utils/__init__.py
acto/utils/time.py
acto_cli/__init__.py
acto_cli/main.py
acto_cli/commands/__init__.py
acto_cli/commands/access.py
acto_cli/commands/completion.py
acto_cli/commands/interactive.py
acto_cli/commands/keys.py
acto_cli/commands/pipeline.py
acto_cli/commands/plugins.py
acto_cli/commands/proof.py
actobotics-1.0.0.dist-info/METADATA
actobotics-1.0.0.dist-info/WHEEL
actobotics-1.0.0.dist-info/entry_points.txt
actobotics-1.0.0.dist-info/licenses/LICENSE
actobotics-1.0.0.dist-info/RECORD
