Metadata-Version: 2.4
Name: actobotics
Version: 1.0.0
Summary: Robotics proof-of-execution SDK
Project-URL: Homepage, https://actobotics.net
Project-URL: Documentation, https://api.actobotics.net/dashboard
Project-URL: Repository, https://github.com/actobotics/ACTO
Project-URL: Issues, https://github.com/actobotics/ACTO/issues
Author: ACTO Contributors
License: MIT License
License-File: LICENSE
Keywords: proof,robotics,solana,telemetry,verification,web3
Classifier: Development Status :: 4 - Beta
Classifier: Intended Audience :: Developers
Classifier: License :: OSI Approved :: MIT License
Classifier: Programming Language :: Python :: 3
Classifier: Programming Language :: Python :: 3.10
Classifier: Programming Language :: Python :: 3.11
Classifier: Programming Language :: Python :: 3.12
Classifier: Topic :: Scientific/Engineering :: Artificial Intelligence
Classifier: Topic :: Software Development :: Libraries :: Python Modules
Requires-Python: >=3.10
Requires-Dist: blake3>=0.4.1
Requires-Dist: cryptography>=42.0
Requires-Dist: httpx>=0.27
Requires-Dist: orjson>=3.10
Requires-Dist: pydantic-settings>=2.3
Requires-Dist: pydantic>=2.7
Requires-Dist: pyjwt>=2.8
Requires-Dist: pynacl>=1.5.0
Requires-Dist: python-json-logger>=2.0.7
Requires-Dist: rich>=13.7
Requires-Dist: sqlalchemy>=2.0
Requires-Dist: tenacity>=8.2
Requires-Dist: typer>=0.12
Provides-Extra: all
Requires-Dist: alembic>=1.13; extra == 'all'
Requires-Dist: bandit>=1.7; extra == 'all'
Requires-Dist: boto3>=1.34.0; extra == 'all'
Requires-Dist: build>=1.0; extra == 'all'
Requires-Dist: coverage>=7.5; extra == 'all'
Requires-Dist: fastapi>=0.112; extra == 'all'
Requires-Dist: hvac>=1.2.0; extra == 'all'
Requires-Dist: hypothesis>=6.100; extra == 'all'
Requires-Dist: locust>=2.24; extra == 'all'
Requires-Dist: mangum>=0.17.0; extra == 'all'
Requires-Dist: mypy>=1.11; extra == 'all'
Requires-Dist: pandas>=2.0.0; extra == 'all'
Requires-Dist: pre-commit>=3.6; extra == 'all'
Requires-Dist: protobuf>=5.0.0; extra == 'all'
Requires-Dist: pyarrow>=15.0.0; extra == 'all'
Requires-Dist: pytest-asyncio>=0.23; extra == 'all'
Requires-Dist: pytest-cov>=5.0; extra == 'all'
Requires-Dist: pytest-timeout>=2.2; extra == 'all'
Requires-Dist: pytest-xdist>=3.5; extra == 'all'
Requires-Dist: pytest>=8.2; extra == 'all'
Requires-Dist: rclpy>=3.3.0; extra == 'all'
Requires-Dist: redis>=5.0; extra == 'all'
Requires-Dist: rosbag2>=0.24.0; extra == 'all'
Requires-Dist: ruff>=0.6.9; extra == 'all'
Requires-Dist: safety>=3.0; extra == 'all'
Requires-Dist: sqlalchemy>=2.0; extra == 'all'
Requires-Dist: twine>=5.0; extra == 'all'
Requires-Dist: uvicorn[standard]>=0.30; extra == 'all'
Provides-Extra: aws
Requires-Dist: boto3>=1.34.0; extra == 'aws'
Provides-Extra: dev
Requires-Dist: alembic>=1.13; extra == 'dev'
Requires-Dist: bandit>=1.7; extra == 'dev'
Requires-Dist: build>=1.0; extra == 'dev'
Requires-Dist: coverage>=7.5; extra == 'dev'
Requires-Dist: fastapi>=0.112; extra == 'dev'
Requires-Dist: hypothesis>=6.100; extra == 'dev'
Requires-Dist: locust>=2.24; extra == 'dev'
Requires-Dist: mangum>=0.17.0; extra == 'dev'
Requires-Dist: mypy>=1.11; extra == 'dev'
Requires-Dist: pre-commit>=3.6; extra == 'dev'
Requires-Dist: pytest-asyncio>=0.23; extra == 'dev'
Requires-Dist: pytest-cov>=5.0; extra == 'dev'
Requires-Dist: pytest-timeout>=2.2; extra == 'dev'
Requires-Dist: pytest-xdist>=3.5; extra == 'dev'
Requires-Dist: pytest>=8.2; extra == 'dev'
Requires-Dist: ruff>=0.6.9; extra == 'dev'
Requires-Dist: safety>=3.0; extra == 'dev'
Requires-Dist: sqlalchemy>=2.0; extra == 'dev'
Requires-Dist: twine>=5.0; extra == 'dev'
Requires-Dist: uvicorn[standard]>=0.30; extra == 'dev'
Provides-Extra: full
Requires-Dist: boto3>=1.34.0; extra == 'full'
Requires-Dist: hvac>=1.2.0; extra == 'full'
Requires-Dist: pandas>=2.0.0; extra == 'full'
Requires-Dist: protobuf>=5.0.0; extra == 'full'
Requires-Dist: pyarrow>=15.0.0; extra == 'full'
Requires-Dist: rclpy>=3.3.0; extra == 'full'
Requires-Dist: redis>=5.0; extra == 'full'
Requires-Dist: rosbag2>=0.24.0; extra == 'full'
Provides-Extra: mysql
Requires-Dist: mysqlclient>=2.2; extra == 'mysql'
Provides-Extra: parquet
Requires-Dist: pandas>=2.0.0; extra == 'parquet'
Requires-Dist: pyarrow>=15.0.0; extra == 'parquet'
Provides-Extra: protobuf
Requires-Dist: protobuf>=5.0.0; extra == 'protobuf'
Provides-Extra: psycopg2
Requires-Dist: psycopg2-binary>=2.9; extra == 'psycopg2'
Provides-Extra: redis
Requires-Dist: redis>=5.0; extra == 'redis'
Provides-Extra: ros
Requires-Dist: rclpy>=3.3.0; extra == 'ros'
Requires-Dist: rosbag2>=0.24.0; extra == 'ros'
Provides-Extra: security
Requires-Dist: boto3>=1.34.0; extra == 'security'
Requires-Dist: hvac>=1.2.0; extra == 'security'
Provides-Extra: server
Requires-Dist: alembic>=1.13; extra == 'server'
Requires-Dist: fastapi>=0.112; extra == 'server'
Requires-Dist: mangum>=0.17.0; extra == 'server'
Requires-Dist: sqlalchemy>=2.0; extra == 'server'
Requires-Dist: uvicorn[standard]>=0.30; extra == 'server'
Provides-Extra: vault
Requires-Dist: hvac>=1.2.0; extra == 'vault'
